datagouv/__init__.py
datagouv/base_object.py
datagouv/client.py
datagouv/dataset.py
datagouv/organization.py
datagouv/resource.py
datagouv/retry.py
datagouv/topic.py
datagouv_client-0.2.3.dist-info/licenses/LICENSE
datagouv_client-0.2.3.dist-info/METADATA
datagouv_client-0.2.3.dist-info/WHEEL
datagouv_client-0.2.3.dist-info/top_level.txt
datagouv_client-0.2.3.dist-info/RECORD
