Metadata-Version: 2.4
Name: datagouv_client
Version: 0.2.3
Summary: Wrapper for the data.gouv.fr API
Author-email: Etalab <opendatateam@data.gouv.fr>
License-Expression: MIT
Project-URL: Source, https://github.com/datagouv/datagouv_client
Keywords: api,wrapper,datagouv
Requires-Python: <3.14,>=3.10
License-File: LICENSE
Requires-Dist: httpx<1,>=0.28.1
Requires-Dist: tenacity<10,>=9.0.0
Provides-Extra: dev
Requires-Dist: httpx<1,>=0.28.1; extra == "dev"
Requires-Dist: pytest-httpx<1,>=0.35.0; extra == "dev"
Requires-Dist: ruff>=0.11.2; extra == "dev"
Dynamic: license-file
